sskit/__init__.py
sskit/camera.py
sskit/coco.py
sskit/metric.py
sskit/utils.py
sskit/version.py
sskit-0.2.5.dist-info/METADATA
sskit-0.2.5.dist-info/WHEEL
sskit-0.2.5.dist-info/top_level.txt
sskit-0.2.5.dist-info/RECORD
