Metadata-Version: 2.4
Name: sskit
Version: 0.2.5
Summary: Spiideo Scenes development Kit
Home-page: https://github.com/Spiideo/sskit
Author: Hakan Ardo
Author-email: hakan.ardo@spiideo.com
License: MIT
Dynamic: author
Dynamic: author-email
Dynamic: description
Dynamic: home-page
Dynamic: license
Dynamic: summary
